{"cameraMode":{"drawMode":0,"name":"Shaded","section":"Shading Mode"},"sceneLighting":true,"audioPlay":false,"sceneViewState":{"m_AlwaysRefresh":false,"showFog":true,"showSkybox":true,"showFlares":true,"showImageEffects":true,"showParticleSystems":true,"showVisualEffectGraphs":true,"m_FxEnabled":true},"in2DMode":false,"pivot":{"x":94.96430206298828,"y":-667.9039306640625,"z":757.459228515625},"rotation":{"x":-0.39073020219802859,"y":-0.00470137782394886,"z":0.0019514055456966162,"w":-0.920579731464386},"size":990.8920288085938,"orthographic":false}